{
  "action": {
    "description": "Introduced by Senators Quinn, James and Marklein; \ncosponsored by Representatives Green, B. Jacobson, Piwowarczyk, Brill, Dittrich, Duchow, Goeben, Gundrum, Hurd, Kitchens, Knodl, Kreibich, Maxey, Melotik, Murphy, Novak, Penterman, Petersen, Snyder, Summerfield and Tittl",
    "date": "2025-09-29T05:00:00+00:00",
    "organization_id": "~{\"classification\": \"upper\"}",
    "classification": [
      "introduction"
    ],
    "related_entities": []
  },
  "bill_id": "SB432"
}