{
  "legislative_session": "2025",
  "identifier": "AB220",
  "title": "Relating to: discrimination in employment, housing, public accommodations, education, insurance coverage, national guard, jury duty, and adoption and in the receipt of mental health or vocational rehabilitation services.",
  "from_organization": "~{\"classification\": \"lower\"}",
  "classification": [
    "bill"
  ],
  "subject": [],
  "abstracts": [],
  "other_titles": [],
  "other_identifiers": [],
  "actions": [
    {
      "description": "Introduced by Representatives Phelps, Neubauer, Arney, Clancy, Cruz, Rivera-Wagner, Snodgrass, Stroud, Udell, Anderson, Bare, Billings, Brown, DeSmidt, Emerson, Fitzgerald, Hong, Joers, Johnson, Kirsch, Madison, Mayadev, Miresse, Moore Omokunde, Ortiz-Velez, Palmeri, Sinicki, Subeck and Tenorio; \ncosponsored by Senators Spreitzer, Ratcliff, Carpenter, Dassler-Alfheim, Roys, Drake, Hesselbein, Keyeski, Larson and Smith",
      "date": "2025-04-23T05:00:00+00:00",
      "organization_id": "~{\"classification\": \"lower\"}",
      "classification": [
        "introduction"
      ],
      "related_entities": [],
      "_processing": {
        "log_file_created": "2025-10-25T03:02:27Z"
      }
    },
    {
      "description": "Read first time and referred to Committee on Workforce Development, Labor, and Integrated Employment",
      "date": "2025-04-23T05:00:00+00:00",
      "organization_id": "~{\"classification\": \"lower\"}",
      "classification": [
        "reading-1",
        "referral-committee"
      ],
      "related_entities": [],
      "_processing": {
        "log_file_created": "2025-10-25T03:02:27Z"
      }
    },
    {
      "description": "Representative Prado added as a coauthor",
      "date": "2025-05-09T05:00:00+00:00",
      "organization_id": "~{\"classification\": \"lower\"}",
      "classification": [],
      "related_entities": [],
      "_processing": {
        "log_file_created": "2025-10-25T03:02:27Z"
      }
    },
    {
      "description": "Representative Haywood added as a coauthor",
      "date": "2025-05-13T05:00:00+00:00",
      "organization_id": "~{\"classification\": \"lower\"}",
      "classification": [],
      "related_entities": [],
      "_processing": {
        "log_file_created": "2025-10-25T03:02:27Z"
      }
    }
  ],
  "sponsorships": [
    {
      "name": "Phelps",
      "classification": "primary",
      "entity_type": "person",
      "primary": true,
      "person_id": "~{\"chamber\": \"lower\", \"name\": \"Phelps\"}",
      "organization_id": null
    },
    {
      "name": "Neubauer",
      "classification": "primary",
      "entity_type": "person",
      "primary": true,
      "person_id": "~{\"chamber\": \"lower\", \"name\": \"Neubauer\"}",
      "organization_id": null
    },
    {
      "name": "Arney",
      "classification": "primary",
      "entity_type": "person",
      "primary": true,
      "person_id": "~{\"chamber\": \"lower\", \"name\": \"Arney\"}",
      "organization_id": null
    },
    {
      "name": "Clancy",
      "classification": "primary",
      "entity_type": "person",
      "primary": true,
      "person_id": "~{\"chamber\": \"lower\", \"name\": \"Clancy\"}",
      "organization_id": null
    },
    {
      "name": "Cruz",
      "classification": "primary",
      "entity_type": "person",
      "primary": true,
      "person_id": "~{\"chamber\": \"lower\", \"name\": \"Cruz\"}",
      "organization_id": null
    },
    {
      "name": "Rivera-Wagner",
      "classification": "primary",
      "entity_type": "person",
      "primary": true,
      "person_id": "~{\"chamber\": \"lower\", \"name\": \"Rivera-Wagner\"}",
      "organization_id": null
    },
    {
      "name": "Snodgrass",
      "classification": "primary",
      "entity_type": "person",
      "primary": true,
      "person_id": "~{\"chamber\": \"lower\", \"name\": \"Snodgrass\"}",
      "organization_id": null
    },
    {
      "name": "Stroud",
      "classification": "primary",
      "entity_type": "person",
      "primary": true,
      "person_id": "~{\"chamber\": \"lower\", \"name\": \"Stroud\"}",
      "organization_id": null
    },
    {
      "name": "Udell",
      "classification": "primary",
      "entity_type": "person",
      "primary": true,
      "person_id": "~{\"chamber\": \"lower\", \"name\": \"Udell\"}",
      "organization_id": null
    },
    {
      "name": "Anderson",
      "classification": "primary",
      "entity_type": "person",
      "primary": true,
      "person_id": "~{\"chamber\": \"lower\", \"name\": \"Anderson\"}",
      "organization_id": null
    },
    {
      "name": "Bare",
      "classification": "primary",
      "entity_type": "person",
      "primary": true,
      "person_id": "~{\"chamber\": \"lower\", \"name\": \"Bare\"}",
      "organization_id": null
    },
    {
      "name": "Billings",
      "classification": "primary",
      "entity_type": "person",
      "primary": true,
      "person_id": "~{\"chamber\": \"lower\", \"name\": \"Billings\"}",
      "organization_id": null
    },
    {
      "name": "Brown",
      "classification": "primary",
      "entity_type": "person",
      "primary": true,
      "person_id": "~{\"chamber\": \"lower\", \"name\": \"Brown\"}",
      "organization_id": null
    },
    {
      "name": "DeSmidt",
      "classification": "primary",
      "entity_type": "person",
      "primary": true,
      "person_id": "~{\"chamber\": \"lower\", \"name\": \"DeSmidt\"}",
      "organization_id": null
    },
    {
      "name": "Emerson",
      "classification": "primary",
      "entity_type": "person",
      "primary": true,
      "person_id": "~{\"chamber\": \"lower\", \"name\": \"Emerson\"}",
      "organization_id": null
    },
    {
      "name": "Fitzgerald",
      "classification": "primary",
      "entity_type": "person",
      "primary": true,
      "person_id": "~{\"chamber\": \"lower\", \"name\": \"Fitzgerald\"}",
      "organization_id": null
    },
    {
      "name": "Hong",
      "classification": "primary",
      "entity_type": "person",
      "primary": true,
      "person_id": "~{\"chamber\": \"lower\", \"name\": \"Hong\"}",
      "organization_id": null
    },
    {
      "name": "Joers",
      "classification": "primary",
      "entity_type": "person",
      "primary": true,
      "person_id": "~{\"chamber\": \"lower\", \"name\": \"Joers\"}",
      "organization_id": null
    },
    {
      "name": "Johnson",
      "classification": "primary",
      "entity_type": "person",
      "primary": true,
      "person_id": "~{\"chamber\": \"lower\", \"name\": \"Johnson\"}",
      "organization_id": null
    },
    {
      "name": "Kirsch",
      "classification": "primary",
      "entity_type": "person",
      "primary": true,
      "person_id": "~{\"chamber\": \"lower\", \"name\": \"Kirsch\"}",
      "organization_id": null
    },
    {
      "name": "Madison",
      "classification": "primary",
      "entity_type": "person",
      "primary": true,
      "person_id": "~{\"chamber\": \"lower\", \"name\": \"Madison\"}",
      "organization_id": null
    },
    {
      "name": "Mayadev",
      "classification": "primary",
      "entity_type": "person",
      "primary": true,
      "person_id": "~{\"chamber\": \"lower\", \"name\": \"Mayadev\"}",
      "organization_id": null
    },
    {
      "name": "Miresse",
      "classification": "primary",
      "entity_type": "person",
      "primary": true,
      "person_id": "~{\"chamber\": \"lower\", \"name\": \"Miresse\"}",
      "organization_id": null
    },
    {
      "name": "Moore Omokunde",
      "classification": "primary",
      "entity_type": "person",
      "primary": true,
      "person_id": "~{\"chamber\": \"lower\", \"name\": \"Moore Omokunde\"}",
      "organization_id": null
    },
    {
      "name": "Ortiz-Velez",
      "classification": "primary",
      "entity_type": "person",
      "primary": true,
      "person_id": "~{\"chamber\": \"lower\", \"name\": \"Ortiz-Velez\"}",
      "organization_id": null
    },
    {
      "name": "Palmeri",
      "classification": "primary",
      "entity_type": "person",
      "primary": true,
      "person_id": "~{\"chamber\": \"lower\", \"name\": \"Palmeri\"}",
      "organization_id": null
    },
    {
      "name": "Sinicki",
      "classification": "primary",
      "entity_type": "person",
      "primary": true,
      "person_id": "~{\"chamber\": \"lower\", \"name\": \"Sinicki\"}",
      "organization_id": null
    },
    {
      "name": "Subeck",
      "classification": "primary",
      "entity_type": "person",
      "primary": true,
      "person_id": "~{\"chamber\": \"lower\", \"name\": \"Subeck\"}",
      "organization_id": null
    },
    {
      "name": "Tenorio",
      "classification": "primary",
      "entity_type": "person",
      "primary": true,
      "person_id": "~{\"chamber\": \"lower\", \"name\": \"Tenorio\"}",
      "organization_id": null
    }
  ],
  "related_bills": [],
  "versions": [
    {
      "note": "Bill Text",
      "links": [
        {
          "url": "https://docs.legis.wisconsin.gov/document/proposaltext/2025/REG/AB220",
          "media_type": "text/html"
        },
        {
          "url": "https://docs.legis.wisconsin.gov/document/proposaltext/2025/REG/AB220.pdf",
          "media_type": "application/pdf"
        }
      ],
      "date": "",
      "classification": ""
    }
  ],
  "documents": [
    {
      "note": "Wisconsin Ethics Commission information",
      "links": [
        {
          "url": "https://lobbying.wi.gov/What/BillInformation/2025REG/BillKey/REGAB220",
          "media_type": "text/html"
        }
      ],
      "date": "",
      "classification": ""
    },
    {
      "note": "2025 Senate Bill 223",
      "links": [
        {
          "url": "https://docs.legis.wisconsin.gov/2025/proposals/sb223",
          "media_type": "text/html"
        }
      ],
      "date": "",
      "classification": ""
    }
  ],
  "citations": [],
  "sources": [
    {
      "url": "https://docs.legis.wisconsin.gov/2025/proposals/reg/asm/bill/ab220",
      "note": ""
    }
  ],
  "extras": {
    "status": "Status: A - Workforce Development, Labor, and Integrated Employment"
  },
  "jurisdiction": {
    "id": "ocd-jurisdiction/country:us/state:wi/government",
    "name": "Wisconsin",
    "classification": "state",
    "division_id": "ocd-division/country:us/state:wi"
  },
  "_processing": {
    "logs_latest_update": "2025-10-25T03:02:27Z",
    "text_extraction_latest_update": "2025-10-25T09:00:26.007026Z"
  }
}