{
  "legislative_session": "2025",
  "identifier": "AB257",
  "title": "Relating to: advanced practice registered nurses, extending the time limit for emergency rule procedures, providing an exemption from emergency rule procedures, and granting rule-making authority. (FE)",
  "from_organization": "~{\"classification\": \"lower\"}",
  "classification": [
    "bill"
  ],
  "subject": [],
  "abstracts": [],
  "other_titles": [],
  "other_identifiers": [],
  "actions": [
    {
      "description": "Introduced by Representatives Kurtz, Subeck, Rodriguez, Andraca, Behnke, Brown, Cruz, DeSmidt, Emerson, Gundrum, Joers, Kreibich, Maxey, Murphy, O'Connor, Ortiz-Velez, Prado, Spiros, Stubbs, Tusler, Udell and Wichgers; \ncosponsored by Senators Testin, Cabral-Guevara, Roys, Dassler-Alfheim, Habush Sinykin, Hesselbein, Keyeski, LeMahieu, Marklein, Quinn, Ratcliff, Smith and Spreitzer",
      "date": "2025-05-12T05:00:00+00:00",
      "organization_id": "~{\"classification\": \"lower\"}",
      "classification": [
        "introduction"
      ],
      "related_entities": [],
      "_processing": {
        "log_file_created": "2025-10-25T03:02:26Z"
      }
    },
    {
      "description": "Read first time and referred to Committee on Health, Aging and Long-Term Care",
      "date": "2025-05-12T05:00:00+00:00",
      "organization_id": "~{\"classification\": \"lower\"}",
      "classification": [
        "reading-1",
        "referral-committee"
      ],
      "related_entities": [],
      "_processing": {
        "log_file_created": "2025-10-25T03:02:26Z"
      }
    },
    {
      "description": "Representatives Donovan and Palmeri added as coauthors",
      "date": "2025-05-12T05:00:00+00:00",
      "organization_id": "~{\"classification\": \"lower\"}",
      "classification": [],
      "related_entities": [],
      "_processing": {
        "log_file_created": "2025-10-25T03:02:26Z"
      }
    },
    {
      "description": "Senator Jacque added as a cosponsor",
      "date": "2025-05-13T05:00:00+00:00",
      "organization_id": "~{\"classification\": \"lower\"}",
      "classification": [],
      "related_entities": [],
      "_processing": {
        "log_file_created": "2025-10-25T03:02:26Z"
      }
    },
    {
      "description": "Representatives McCarville, Miresse, Goeben and Knodl added as coauthors",
      "date": "2025-05-13T05:00:00+00:00",
      "organization_id": "~{\"classification\": \"lower\"}",
      "classification": [],
      "related_entities": [],
      "_processing": {
        "log_file_created": "2025-10-25T03:02:26Z"
      }
    },
    {
      "description": "Fiscal estimate received",
      "date": "2025-05-13T05:00:00+00:00",
      "organization_id": "~{\"classification\": \"lower\"}",
      "classification": [
        "receipt"
      ],
      "related_entities": [],
      "_processing": {
        "log_file_created": "2025-10-25T03:02:26Z"
      }
    },
    {
      "description": "Representative Kitchens added as a coauthor",
      "date": "2025-05-14T05:00:00+00:00",
      "organization_id": "~{\"classification\": \"lower\"}",
      "classification": [],
      "related_entities": [],
      "_processing": {
        "log_file_created": "2025-10-25T03:02:26Z"
      }
    },
    {
      "description": "Public hearing held",
      "date": "2025-05-14T05:00:00+00:00",
      "organization_id": "~{\"classification\": \"lower\"}",
      "classification": [],
      "related_entities": [],
      "_processing": {
        "log_file_created": "2025-10-25T03:02:26Z"
      }
    },
    {
      "description": "Representative Vining added as a coauthor",
      "date": "2025-05-15T05:00:00+00:00",
      "organization_id": "~{\"classification\": \"lower\"}",
      "classification": [],
      "related_entities": [],
      "_processing": {
        "log_file_created": "2025-10-25T03:02:26Z"
      }
    },
    {
      "description": "Representative Clancy added as a coauthor",
      "date": "2025-05-19T05:00:00+00:00",
      "organization_id": "~{\"classification\": \"lower\"}",
      "classification": [],
      "related_entities": [],
      "_processing": {
        "log_file_created": "2025-10-25T03:02:26Z"
      }
    },
    {
      "description": "Representative Madison added as a coauthor",
      "date": "2025-05-20T05:00:00+00:00",
      "organization_id": "~{\"classification\": \"lower\"}",
      "classification": [],
      "related_entities": [],
      "_processing": {
        "log_file_created": "2025-10-25T03:02:26Z"
      }
    },
    {
      "description": "Senators James and Larson added as cosponsors",
      "date": "2025-05-29T05:00:00+00:00",
      "organization_id": "~{\"classification\": \"lower\"}",
      "classification": [],
      "related_entities": [],
      "_processing": {
        "log_file_created": "2025-10-25T03:02:26Z"
      }
    },
    {
      "description": "Fiscal estimate received",
      "date": "2025-05-30T05:00:00+00:00",
      "organization_id": "~{\"classification\": \"lower\"}",
      "classification": [
        "receipt"
      ],
      "related_entities": [],
      "_processing": {
        "log_file_created": "2025-10-25T03:02:26Z"
      }
    },
    {
      "description": "Representative Snodgrass added as a coauthor",
      "date": "2025-05-30T05:00:00+00:00",
      "organization_id": "~{\"classification\": \"lower\"}",
      "classification": [],
      "related_entities": [],
      "_processing": {
        "log_file_created": "2025-10-25T03:02:26Z"
      }
    },
    {
      "description": "Representative Moses added as a coauthor",
      "date": "2025-06-04T05:00:00+00:00",
      "organization_id": "~{\"classification\": \"lower\"}",
      "classification": [],
      "related_entities": [],
      "_processing": {
        "log_file_created": "2025-10-25T03:02:26Z"
      }
    },
    {
      "description": "Executive action taken",
      "date": "2025-06-04T05:00:00+00:00",
      "organization_id": "~{\"classification\": \"lower\"}",
      "classification": [],
      "related_entities": [],
      "_processing": {
        "log_file_created": "2025-10-25T03:02:26Z"
      }
    },
    {
      "description": "Fiscal estimate received",
      "date": "2025-06-06T05:00:00+00:00",
      "organization_id": "~{\"classification\": \"lower\"}",
      "classification": [
        "receipt"
      ],
      "related_entities": [],
      "_processing": {
        "log_file_created": "2025-10-25T03:02:26Z"
      }
    },
    {
      "description": "Report passage recommended by Committee on Health, Aging and Long-Term Care, Ayes 15, Noes 0",
      "date": "2025-06-06T05:00:00+00:00",
      "organization_id": "~{\"classification\": \"lower\"}",
      "classification": [
        "committee-passage-favorable"
      ],
      "related_entities": [],
      "_processing": {
        "log_file_created": "2025-10-25T03:02:26Z"
      }
    },
    {
      "description": "Referred to committee on Rules",
      "date": "2025-06-06T05:00:00+00:00",
      "organization_id": "~{\"classification\": \"lower\"}",
      "classification": [
        "referral-committee"
      ],
      "related_entities": [],
      "_processing": {
        "log_file_created": "2025-10-25T03:02:26Z"
      }
    },
    {
      "description": "Withdrawn from committee on Rules and referred to calendar of 6-18-2025",
      "date": "2025-06-16T05:00:00+00:00",
      "organization_id": "~{\"classification\": \"lower\"}",
      "classification": [],
      "related_entities": [],
      "_processing": {
        "log_file_created": "2025-10-25T03:02:26Z"
      }
    },
    {
      "description": "Read a second time",
      "date": "2025-06-18T05:00:00+00:00",
      "organization_id": "~{\"classification\": \"lower\"}",
      "classification": [
        "reading-2"
      ],
      "related_entities": [],
      "_processing": {
        "log_file_created": "2025-10-25T03:02:26Z"
      }
    },
    {
      "description": "Ordered to a third reading",
      "date": "2025-06-18T05:00:00+00:00",
      "organization_id": "~{\"classification\": \"lower\"}",
      "classification": [
        "reading-3"
      ],
      "related_entities": [],
      "_processing": {
        "log_file_created": "2025-10-25T03:02:26Z"
      }
    },
    {
      "description": "Rules suspended",
      "date": "2025-06-18T05:00:00+00:00",
      "organization_id": "~{\"classification\": \"lower\"}",
      "classification": [],
      "related_entities": [],
      "_processing": {
        "log_file_created": "2025-10-25T03:02:26Z"
      }
    },
    {
      "description": "Read a third time and passed",
      "date": "2025-06-18T05:00:00+00:00",
      "organization_id": "~{\"classification\": \"lower\"}",
      "classification": [
        "passage",
        "reading-3"
      ],
      "related_entities": [],
      "_processing": {
        "log_file_created": "2025-10-25T03:02:26Z"
      }
    },
    {
      "description": "Ordered immediately messaged",
      "date": "2025-06-18T05:00:00+00:00",
      "organization_id": "~{\"classification\": \"lower\"}",
      "classification": [],
      "related_entities": [],
      "_processing": {
        "log_file_created": "2025-10-25T03:02:26Z"
      }
    },
    {
      "description": "Received from Assembly",
      "date": "2025-06-18T05:00:00+00:00",
      "organization_id": "~{\"classification\": \"upper\"}",
      "classification": [
        "receipt"
      ],
      "related_entities": [],
      "_processing": {
        "log_file_created": "2025-10-25T03:02:26Z"
      }
    },
    {
      "description": "Senator Carpenter added as a cosponsor",
      "date": "2025-06-18T05:00:00+00:00",
      "organization_id": "~{\"classification\": \"upper\"}",
      "classification": [],
      "related_entities": [],
      "_processing": {
        "log_file_created": "2025-10-25T03:02:26Z"
      }
    },
    {
      "description": "Rules suspended and taken up",
      "date": "2025-06-18T05:00:00+00:00",
      "organization_id": "~{\"classification\": \"upper\"}",
      "classification": [],
      "related_entities": [],
      "_processing": {
        "log_file_created": "2025-10-25T03:02:26Z"
      }
    },
    {
      "description": "Read a second time",
      "date": "2025-06-18T05:00:00+00:00",
      "organization_id": "~{\"classification\": \"upper\"}",
      "classification": [
        "reading-2"
      ],
      "related_entities": [],
      "_processing": {
        "log_file_created": "2025-10-25T03:02:26Z"
      }
    },
    {
      "description": "Ordered to a third reading",
      "date": "2025-06-18T05:00:00+00:00",
      "organization_id": "~{\"classification\": \"upper\"}",
      "classification": [
        "reading-3"
      ],
      "related_entities": [],
      "_processing": {
        "log_file_created": "2025-10-25T03:02:26Z"
      }
    },
    {
      "description": "Rules suspended to give bill its third reading",
      "date": "2025-06-18T05:00:00+00:00",
      "organization_id": "~{\"classification\": \"upper\"}",
      "classification": [],
      "related_entities": [],
      "_processing": {
        "log_file_created": "2025-10-25T03:02:26Z"
      }
    },
    {
      "description": "Read a third time and concurred in",
      "date": "2025-06-18T05:00:00+00:00",
      "organization_id": "~{\"classification\": \"upper\"}",
      "classification": [
        "passage",
        "reading-3"
      ],
      "related_entities": [],
      "_processing": {
        "log_file_created": "2025-10-25T03:02:26Z"
      }
    },
    {
      "description": "Ordered immediately messaged",
      "date": "2025-06-18T05:00:00+00:00",
      "organization_id": "~{\"classification\": \"upper\"}",
      "classification": [],
      "related_entities": [],
      "_processing": {
        "log_file_created": "2025-10-25T03:02:26Z"
      }
    },
    {
      "description": "Received from Senate concurred in",
      "date": "2025-06-19T05:00:00+00:00",
      "organization_id": "~{\"classification\": \"lower\"}",
      "classification": [
        "receipt"
      ],
      "related_entities": [],
      "_processing": {
        "log_file_created": "2025-10-25T03:02:26Z"
      }
    },
    {
      "description": "Fiscal estimate received",
      "date": "2025-06-19T05:00:00+00:00",
      "organization_id": "~{\"classification\": \"lower\"}",
      "classification": [
        "receipt"
      ],
      "related_entities": [],
      "_processing": {
        "log_file_created": "2025-10-25T03:02:26Z"
      }
    },
    {
      "description": "Report correctly enrolled on 6-23-2025",
      "date": "2025-06-23T05:00:00+00:00",
      "organization_id": "~{\"classification\": \"lower\"}",
      "classification": [
        "enrolled"
      ],
      "related_entities": [],
      "_processing": {
        "log_file_created": "2025-10-25T03:02:26Z"
      }
    },
    {
      "description": "Presented to the Governor on 8-7-2025",
      "date": "2025-08-07T05:00:00+00:00",
      "organization_id": "~{\"classification\": \"lower\"}",
      "classification": [
        "executive-receipt"
      ],
      "related_entities": [],
      "_processing": {
        "log_file_created": "2025-10-25T03:02:26Z"
      }
    },
    {
      "description": "Report approved by the Governor on 8-8-2025. 2025 Wisconsin Act 17",
      "date": "2025-08-11T05:00:00+00:00",
      "organization_id": "~{\"classification\": \"lower\"}",
      "classification": [
        "executive-signature"
      ],
      "related_entities": [],
      "_processing": {
        "log_file_created": "2025-10-25T03:02:26Z"
      }
    },
    {
      "description": "Published 8-9-2025",
      "date": "2025-08-11T05:00:00+00:00",
      "organization_id": "~{\"classification\": \"lower\"}",
      "classification": [
        "became-law"
      ],
      "related_entities": [],
      "_processing": {
        "log_file_created": "2025-10-25T03:02:26Z"
      }
    },
    {
      "description": "Representative J. Jacobson added as a coauthor",
      "date": "2025-09-09T05:00:00+00:00",
      "organization_id": "~{\"classification\": \"lower\"}",
      "classification": [],
      "related_entities": [],
      "_processing": {
        "log_file_created": "2025-10-25T03:02:26Z"
      }
    }
  ],
  "sponsorships": [
    {
      "name": "Kurtz",
      "classification": "primary",
      "entity_type": "person",
      "primary": true,
      "person_id": "~{\"chamber\": \"lower\", \"name\": \"Kurtz\"}",
      "organization_id": null
    },
    {
      "name": "Subeck",
      "classification": "primary",
      "entity_type": "person",
      "primary": true,
      "person_id": "~{\"chamber\": \"lower\", \"name\": \"Subeck\"}",
      "organization_id": null
    },
    {
      "name": "Rodriguez",
      "classification": "primary",
      "entity_type": "person",
      "primary": true,
      "person_id": "~{\"chamber\": \"lower\", \"name\": \"Rodriguez\"}",
      "organization_id": null
    },
    {
      "name": "Andraca",
      "classification": "primary",
      "entity_type": "person",
      "primary": true,
      "person_id": "~{\"chamber\": \"lower\", \"name\": \"Andraca\"}",
      "organization_id": null
    },
    {
      "name": "Behnke",
      "classification": "primary",
      "entity_type": "person",
      "primary": true,
      "person_id": "~{\"chamber\": \"lower\", \"name\": \"Behnke\"}",
      "organization_id": null
    },
    {
      "name": "Brown",
      "classification": "primary",
      "entity_type": "person",
      "primary": true,
      "person_id": "~{\"chamber\": \"lower\", \"name\": \"Brown\"}",
      "organization_id": null
    },
    {
      "name": "Cruz",
      "classification": "primary",
      "entity_type": "person",
      "primary": true,
      "person_id": "~{\"chamber\": \"lower\", \"name\": \"Cruz\"}",
      "organization_id": null
    },
    {
      "name": "DeSmidt",
      "classification": "primary",
      "entity_type": "person",
      "primary": true,
      "person_id": "~{\"chamber\": \"lower\", \"name\": \"DeSmidt\"}",
      "organization_id": null
    },
    {
      "name": "Emerson",
      "classification": "primary",
      "entity_type": "person",
      "primary": true,
      "person_id": "~{\"chamber\": \"lower\", \"name\": \"Emerson\"}",
      "organization_id": null
    },
    {
      "name": "Gundrum",
      "classification": "primary",
      "entity_type": "person",
      "primary": true,
      "person_id": "~{\"chamber\": \"lower\", \"name\": \"Gundrum\"}",
      "organization_id": null
    },
    {
      "name": "Joers",
      "classification": "primary",
      "entity_type": "person",
      "primary": true,
      "person_id": "~{\"chamber\": \"lower\", \"name\": \"Joers\"}",
      "organization_id": null
    },
    {
      "name": "Kreibich",
      "classification": "primary",
      "entity_type": "person",
      "primary": true,
      "person_id": "~{\"chamber\": \"lower\", \"name\": \"Kreibich\"}",
      "organization_id": null
    },
    {
      "name": "Maxey",
      "classification": "primary",
      "entity_type": "person",
      "primary": true,
      "person_id": "~{\"chamber\": \"lower\", \"name\": \"Maxey\"}",
      "organization_id": null
    },
    {
      "name": "Murphy",
      "classification": "primary",
      "entity_type": "person",
      "primary": true,
      "person_id": "~{\"chamber\": \"lower\", \"name\": \"Murphy\"}",
      "organization_id": null
    },
    {
      "name": "O'Connor",
      "classification": "primary",
      "entity_type": "person",
      "primary": true,
      "person_id": "~{\"chamber\": \"lower\", \"name\": \"O'Connor\"}",
      "organization_id": null
    },
    {
      "name": "Ortiz-Velez",
      "classification": "primary",
      "entity_type": "person",
      "primary": true,
      "person_id": "~{\"chamber\": \"lower\", \"name\": \"Ortiz-Velez\"}",
      "organization_id": null
    },
    {
      "name": "Prado",
      "classification": "primary",
      "entity_type": "person",
      "primary": true,
      "person_id": "~{\"chamber\": \"lower\", \"name\": \"Prado\"}",
      "organization_id": null
    },
    {
      "name": "Spiros",
      "classification": "primary",
      "entity_type": "person",
      "primary": true,
      "person_id": "~{\"chamber\": \"lower\", \"name\": \"Spiros\"}",
      "organization_id": null
    },
    {
      "name": "Stubbs",
      "classification": "primary",
      "entity_type": "person",
      "primary": true,
      "person_id": "~{\"chamber\": \"lower\", \"name\": \"Stubbs\"}",
      "organization_id": null
    },
    {
      "name": "Tusler",
      "classification": "primary",
      "entity_type": "person",
      "primary": true,
      "person_id": "~{\"chamber\": \"lower\", \"name\": \"Tusler\"}",
      "organization_id": null
    },
    {
      "name": "Udell",
      "classification": "primary",
      "entity_type": "person",
      "primary": true,
      "person_id": "~{\"chamber\": \"lower\", \"name\": \"Udell\"}",
      "organization_id": null
    },
    {
      "name": "Wichgers",
      "classification": "primary",
      "entity_type": "person",
      "primary": true,
      "person_id": "~{\"chamber\": \"lower\", \"name\": \"Wichgers\"}",
      "organization_id": null
    }
  ],
  "related_bills": [],
  "versions": [
    {
      "note": "Bill Text",
      "links": [
        {
          "url": "https://docs.legis.wisconsin.gov/document/proposaltext/2025/REG/AB257",
          "media_type": "text/html"
        },
        {
          "url": "https://docs.legis.wisconsin.gov/document/proposaltext/2025/REG/AB257.pdf",
          "media_type": "application/pdf"
        }
      ],
      "date": "",
      "classification": ""
    }
  ],
  "documents": [
    {
      "note": "2025 Wisconsin Act 17",
      "links": [
        {
          "url": "https://docs.legis.wisconsin.gov/document/acts/2025/17",
          "media_type": ""
        }
      ],
      "date": "",
      "classification": ""
    },
    {
      "note": "2025 Wisconsin Act 17: LC Act Memo",
      "links": [
        {
          "url": "https://docs.legis.wisconsin.gov/document/lcactmemos/2025/REG/Act%2017.pdf",
          "media_type": ""
        }
      ],
      "date": "",
      "classification": ""
    },
    {
      "note": "AB257: Fiscal Estimate From DHS",
      "links": [
        {
          "url": "https://docs.legis.wisconsin.gov/2025/related/fe/ab257/ab257_dhs.pdf",
          "media_type": ""
        }
      ],
      "date": "",
      "classification": ""
    },
    {
      "note": "AB257: Fiscal Estimate From DPI",
      "links": [
        {
          "url": "https://docs.legis.wisconsin.gov/2025/related/fe/ab257/ab257_dpi.pdf",
          "media_type": ""
        }
      ],
      "date": "",
      "classification": ""
    },
    {
      "note": "AB257: Fiscal Estimate From DSPS",
      "links": [
        {
          "url": "https://docs.legis.wisconsin.gov/2025/related/fe/ab257/ab257_dsps.pdf",
          "media_type": ""
        }
      ],
      "date": "",
      "classification": ""
    },
    {
      "note": "AB257: Fiscal Estimate From DWD",
      "links": [
        {
          "url": "https://docs.legis.wisconsin.gov/2025/related/fe/ab257/ab257_dwd.pdf",
          "media_type": ""
        }
      ],
      "date": "",
      "classification": ""
    },
    {
      "note": "AB257 ROCP for Committee on Health, Aging and Long-Term Care On 6/6/2025",
      "links": [
        {
          "url": "https://docs.legis.wisconsin.gov/2025/related/records/assembly/health_aging_and_long_term_care/1919663",
          "media_type": "text/html"
        }
      ],
      "date": "",
      "classification": ""
    },
    {
      "note": "LC Bill Hearing Materials",
      "links": [
        {
          "url": "https://docs.legis.wisconsin.gov/document/lcbillhearingtestimonyandmaterials/2025/REG/AB257",
          "media_type": "text/html"
        }
      ],
      "date": "",
      "classification": ""
    },
    {
      "note": "Wisconsin Ethics Commission information",
      "links": [
        {
          "url": "https://lobbying.wi.gov/What/BillInformation/2025REG/BillKey/REGAB257",
          "media_type": "text/html"
        }
      ],
      "date": "",
      "classification": ""
    },
    {
      "note": "2025 Senate Bill 258",
      "links": [
        {
          "url": "https://docs.legis.wisconsin.gov/2025/proposals/sb258",
          "media_type": "text/html"
        }
      ],
      "date": "",
      "classification": ""
    }
  ],
  "citations": [],
  "sources": [
    {
      "url": "https://docs.legis.wisconsin.gov/2025/proposals/reg/asm/bill/ab257",
      "note": ""
    }
  ],
  "extras": {
    "status": "Status: A - Enacted into Law"
  },
  "jurisdiction": {
    "id": "ocd-jurisdiction/country:us/state:wi/government",
    "name": "Wisconsin",
    "classification": "state",
    "division_id": "ocd-division/country:us/state:wi"
  },
  "_processing": {
    "logs_latest_update": "2025-10-25T03:02:26Z",
    "text_extraction_latest_update": "2025-10-25T09:23:45.288320Z"
  }
}