{
  "legislative_session": "2025",
  "identifier": "AB130",
  "title": "Relating to: exempting certain persons from PFAS enforcement actions under the spills law. (FE)",
  "from_organization": "~{\"classification\": \"lower\"}",
  "classification": [
    "bill"
  ],
  "subject": [],
  "abstracts": [],
  "other_titles": [],
  "other_identifiers": [],
  "actions": [
    {
      "description": "Introduced by Representatives Mursau, Swearingen, Armstrong, Behnke, Franklin, Green, Gundrum, B. Jacobson, Knodl, Maxey, Murphy, Novak, O'Connor, Spiros, Steffen, Tucker and Tusler; \ncosponsored by Senators Wimberger, Cabral-Guevara, Felzkowski, Nass and Tomczyk",
      "date": "2025-03-13T05:00:00+00:00",
      "organization_id": "~{\"classification\": \"lower\"}",
      "classification": [
        "introduction"
      ],
      "related_entities": [],
      "_processing": {
        "log_file_created": "2025-10-25T03:02:27Z"
      }
    },
    {
      "description": "Read first time and referred to Committee on Environment",
      "date": "2025-03-13T05:00:00+00:00",
      "organization_id": "~{\"classification\": \"lower\"}",
      "classification": [
        "reading-1",
        "referral-committee"
      ],
      "related_entities": [],
      "_processing": {
        "log_file_created": "2025-10-25T03:02:27Z"
      }
    },
    {
      "description": "Representative Kitchens added as a coauthor",
      "date": "2025-03-14T05:00:00+00:00",
      "organization_id": "~{\"classification\": \"lower\"}",
      "classification": [],
      "related_entities": [],
      "_processing": {
        "log_file_created": "2025-10-25T03:02:27Z"
      }
    },
    {
      "description": "Fiscal estimate received",
      "date": "2025-10-14T05:00:00+00:00",
      "organization_id": "~{\"classification\": \"lower\"}",
      "classification": [
        "receipt"
      ],
      "related_entities": [],
      "_processing": {
        "log_file_created": "2025-10-25T03:02:27Z"
      }
    }
  ],
  "sponsorships": [
    {
      "name": "Mursau",
      "classification": "primary",
      "entity_type": "person",
      "primary": true,
      "person_id": "~{\"chamber\": \"lower\", \"name\": \"Mursau\"}",
      "organization_id": null
    },
    {
      "name": "Swearingen",
      "classification": "primary",
      "entity_type": "person",
      "primary": true,
      "person_id": "~{\"chamber\": \"lower\", \"name\": \"Swearingen\"}",
      "organization_id": null
    },
    {
      "name": "Armstrong",
      "classification": "primary",
      "entity_type": "person",
      "primary": true,
      "person_id": "~{\"chamber\": \"lower\", \"name\": \"Armstrong\"}",
      "organization_id": null
    },
    {
      "name": "Behnke",
      "classification": "primary",
      "entity_type": "person",
      "primary": true,
      "person_id": "~{\"chamber\": \"lower\", \"name\": \"Behnke\"}",
      "organization_id": null
    },
    {
      "name": "Franklin",
      "classification": "primary",
      "entity_type": "person",
      "primary": true,
      "person_id": "~{\"chamber\": \"lower\", \"name\": \"Franklin\"}",
      "organization_id": null
    },
    {
      "name": "Green",
      "classification": "primary",
      "entity_type": "person",
      "primary": true,
      "person_id": "~{\"chamber\": \"lower\", \"name\": \"Green\"}",
      "organization_id": null
    },
    {
      "name": "Gundrum",
      "classification": "primary",
      "entity_type": "person",
      "primary": true,
      "person_id": "~{\"chamber\": \"lower\", \"name\": \"Gundrum\"}",
      "organization_id": null
    },
    {
      "name": "B. Jacobson",
      "classification": "primary",
      "entity_type": "person",
      "primary": true,
      "person_id": "~{\"chamber\": \"lower\", \"name\": \"B. Jacobson\"}",
      "organization_id": null
    },
    {
      "name": "Knodl",
      "classification": "primary",
      "entity_type": "person",
      "primary": true,
      "person_id": "~{\"chamber\": \"lower\", \"name\": \"Knodl\"}",
      "organization_id": null
    },
    {
      "name": "Maxey",
      "classification": "primary",
      "entity_type": "person",
      "primary": true,
      "person_id": "~{\"chamber\": \"lower\", \"name\": \"Maxey\"}",
      "organization_id": null
    },
    {
      "name": "Murphy",
      "classification": "primary",
      "entity_type": "person",
      "primary": true,
      "person_id": "~{\"chamber\": \"lower\", \"name\": \"Murphy\"}",
      "organization_id": null
    },
    {
      "name": "Novak",
      "classification": "primary",
      "entity_type": "person",
      "primary": true,
      "person_id": "~{\"chamber\": \"lower\", \"name\": \"Novak\"}",
      "organization_id": null
    },
    {
      "name": "O'Connor",
      "classification": "primary",
      "entity_type": "person",
      "primary": true,
      "person_id": "~{\"chamber\": \"lower\", \"name\": \"O'Connor\"}",
      "organization_id": null
    },
    {
      "name": "Spiros",
      "classification": "primary",
      "entity_type": "person",
      "primary": true,
      "person_id": "~{\"chamber\": \"lower\", \"name\": \"Spiros\"}",
      "organization_id": null
    },
    {
      "name": "Steffen",
      "classification": "primary",
      "entity_type": "person",
      "primary": true,
      "person_id": "~{\"chamber\": \"lower\", \"name\": \"Steffen\"}",
      "organization_id": null
    },
    {
      "name": "Tucker",
      "classification": "primary",
      "entity_type": "person",
      "primary": true,
      "person_id": "~{\"chamber\": \"lower\", \"name\": \"Tucker\"}",
      "organization_id": null
    },
    {
      "name": "Tusler",
      "classification": "primary",
      "entity_type": "person",
      "primary": true,
      "person_id": "~{\"chamber\": \"lower\", \"name\": \"Tusler\"}",
      "organization_id": null
    }
  ],
  "related_bills": [],
  "versions": [
    {
      "note": "Bill Text",
      "links": [
        {
          "url": "https://docs.legis.wisconsin.gov/document/proposaltext/2025/REG/AB130",
          "media_type": "text/html"
        },
        {
          "url": "https://docs.legis.wisconsin.gov/document/proposaltext/2025/REG/AB130.pdf",
          "media_type": "application/pdf"
        }
      ],
      "date": "",
      "classification": ""
    }
  ],
  "documents": [
    {
      "note": "AB130: Fiscal Estimate From DNR",
      "links": [
        {
          "url": "https://docs.legis.wisconsin.gov/2025/related/fe/ab130/ab130_dnr.pdf",
          "media_type": ""
        }
      ],
      "date": "",
      "classification": ""
    },
    {
      "note": "Wisconsin Ethics Commission information",
      "links": [
        {
          "url": "https://lobbying.wi.gov/What/BillInformation/2025REG/BillKey/REGAB130",
          "media_type": "text/html"
        }
      ],
      "date": "",
      "classification": ""
    },
    {
      "note": "2025 Senate Bill 127",
      "links": [
        {
          "url": "https://docs.legis.wisconsin.gov/2025/proposals/sb127",
          "media_type": "text/html"
        }
      ],
      "date": "",
      "classification": ""
    }
  ],
  "citations": [],
  "sources": [
    {
      "url": "https://docs.legis.wisconsin.gov/2025/proposals/reg/asm/bill/ab130",
      "note": ""
    }
  ],
  "extras": {
    "status": "Status: A - Environment"
  },
  "jurisdiction": {
    "id": "ocd-jurisdiction/country:us/state:wi/government",
    "name": "Wisconsin",
    "classification": "state",
    "division_id": "ocd-division/country:us/state:wi"
  },
  "_processing": {
    "logs_latest_update": "2025-10-25T03:02:27Z",
    "text_extraction_latest_update": "2025-10-25T09:00:55.840852Z"
  }
}