{
  "legislative_session": "2025",
  "identifier": "SB446",
  "title": "Relating to: grants for the provision of immigration-related civil legal services to individuals and families, county grants for the provision of civil legal services to individuals and families, and making an appropriation. (FE)",
  "from_organization": "~{\"classification\": \"upper\"}",
  "classification": [
    "bill"
  ],
  "subject": [],
  "abstracts": [],
  "other_titles": [],
  "other_identifiers": [],
  "actions": [
    {
      "description": "Introduced by Senators Carpenter, Drake, Habush Sinykin, Keyeski, Ratcliff and Spreitzer; \ncosponsored by Representatives Clancy, Rivera-Wagner, Prado, Anderson, Arney, Bare, Brown, DeSanto, DeSmidt, Hong, Joers, Johnson, Kirsch, Madison, Mayadev, Moore Omokunde, Neubauer, Ortiz-Velez, Phelps, Roe, Sheehan, Sinicki, Stroud, Subeck, Taylor, Tenorio, Udell and Haywood",
      "date": "2025-09-29T05:00:00+00:00",
      "organization_id": "~{\"classification\": \"upper\"}",
      "classification": [
        "introduction"
      ],
      "related_entities": [],
      "_processing": {
        "log_file_created": "2025-10-25T03:02:27Z"
      }
    },
    {
      "description": "Read first time and referred to Committee on Licensing, Regulatory Reform, State and Federal Affairs",
      "date": "2025-09-29T05:00:00+00:00",
      "organization_id": "~{\"classification\": \"upper\"}",
      "classification": [
        "reading-1",
        "referral-committee"
      ],
      "related_entities": [],
      "_processing": {
        "log_file_created": "2025-10-25T03:02:27Z"
      }
    }
  ],
  "sponsorships": [
    {
      "name": "Carpenter",
      "classification": "primary",
      "entity_type": "person",
      "primary": true,
      "person_id": "~{\"chamber\": \"upper\", \"name\": \"Carpenter\"}",
      "organization_id": null
    },
    {
      "name": "Drake",
      "classification": "primary",
      "entity_type": "person",
      "primary": true,
      "person_id": "~{\"chamber\": \"upper\", \"name\": \"Drake\"}",
      "organization_id": null
    },
    {
      "name": "Habush Sinykin",
      "classification": "primary",
      "entity_type": "person",
      "primary": true,
      "person_id": "~{\"chamber\": \"upper\", \"name\": \"Habush Sinykin\"}",
      "organization_id": null
    },
    {
      "name": "Keyeski",
      "classification": "primary",
      "entity_type": "person",
      "primary": true,
      "person_id": "~{\"chamber\": \"upper\", \"name\": \"Keyeski\"}",
      "organization_id": null
    },
    {
      "name": "Ratcliff",
      "classification": "primary",
      "entity_type": "person",
      "primary": true,
      "person_id": "~{\"chamber\": \"upper\", \"name\": \"Ratcliff\"}",
      "organization_id": null
    },
    {
      "name": "Spreitzer",
      "classification": "primary",
      "entity_type": "person",
      "primary": true,
      "person_id": "~{\"chamber\": \"upper\", \"name\": \"Spreitzer\"}",
      "organization_id": null
    }
  ],
  "related_bills": [],
  "versions": [
    {
      "note": "Bill Text",
      "links": [
        {
          "url": "https://docs.legis.wisconsin.gov/document/proposaltext/2025/REG/SB446",
          "media_type": "text/html"
        },
        {
          "url": "https://docs.legis.wisconsin.gov/document/proposaltext/2025/REG/SB446.pdf",
          "media_type": "application/pdf"
        }
      ],
      "date": "",
      "classification": ""
    }
  ],
  "documents": [
    {
      "note": "Wisconsin Ethics Commission information",
      "links": [
        {
          "url": "https://lobbying.wi.gov/What/BillInformation/2025REG/BillKey/REGSB446",
          "media_type": "text/html"
        }
      ],
      "date": "",
      "classification": ""
    },
    {
      "note": "2025 Assembly Bill 475",
      "links": [
        {
          "url": "https://docs.legis.wisconsin.gov/2025/proposals/ab475",
          "media_type": "text/html"
        }
      ],
      "date": "",
      "classification": ""
    }
  ],
  "citations": [],
  "sources": [
    {
      "url": "https://docs.legis.wisconsin.gov/2025/proposals/reg/sen/bill/sb446",
      "note": ""
    }
  ],
  "extras": {
    "status": "Status: S - Licensing, Regulatory Reform, State and Federal Affairs"
  },
  "jurisdiction": {
    "id": "ocd-jurisdiction/country:us/state:wi/government",
    "name": "Wisconsin",
    "classification": "state",
    "division_id": "ocd-division/country:us/state:wi"
  },
  "_processing": {
    "logs_latest_update": "2025-10-25T03:02:27Z"
  }
}