{
  "action": {
    "description": "Introduced by Senators Ratcliff, Pfaff, Roys, Larson, Wirch, Drake, Hesselbein, Keyeski and Spreitzer; \ncosponsored by Representatives Udell, Johnson, Sinicki, Stubbs, Roe, Emerson, Brown, Phelps, O'Connor, Arney, Subeck, Bare, J. Jacobson, Fitzgerald, Joers, DeSmidt and Clancy",
    "date": "2025-04-25T05:00:00+00:00",
    "organization_id": "~{\"classification\": \"upper\"}",
    "classification": [
      "introduction"
    ],
    "related_entities": []
  },
  "bill_id": "SJR35"
}