{
  "action": {
    "description": "Introduced by Representatives Kaufert, Franklin, Bare, Behnke, Donovan, Gundrum, Joers, Knodl, Kreibich, Mursau, O'Connor, Palmeri, Snyder, Stubbs, Subeck, Tenorio, Madison, Clancy and Melotik; \ncosponsored by Senators Cabral-Guevara, Testin, Dassler-Alfheim, James, Tomczyk, Wirch, Drake, Ratcliff and Spreitzer",
    "date": "2025-04-15T05:00:00+00:00",
    "organization_id": "~{\"classification\": \"lower\"}",
    "classification": [
      "introduction"
    ],
    "related_entities": []
  },
  "bill_id": "AB176"
}