{
  "legislative_session": "2025",
  "identifier": "SB151",
  "title": "Relating to: requests for information from employers about unemployment insurance claims.",
  "from_organization": "~{\"classification\": \"upper\"}",
  "classification": [
    "bill"
  ],
  "subject": [],
  "abstracts": [],
  "other_titles": [],
  "other_identifiers": [],
  "actions": [
    {
      "description": "Introduced by Senators Hutton, Nass, Tomczyk and Kapenga; \ncosponsored by Representatives Maxey, Armstrong, Brooks, Dittrich, Franklin, Gundrum, Kaufert, Knodl, Melotik, Murphy, Mursau, O'Connor and Spiros",
      "date": "2025-03-21T05:00:00+00:00",
      "organization_id": "~{\"classification\": \"upper\"}",
      "classification": [
        "introduction"
      ],
      "related_entities": [],
      "_processing": {
        "log_file_created": "2025-10-25T03:02:27Z"
      }
    },
    {
      "description": "Read first time and referred to Committee on Government Operations, Labor and Economic Development",
      "date": "2025-03-21T05:00:00+00:00",
      "organization_id": "~{\"classification\": \"upper\"}",
      "classification": [
        "reading-1",
        "referral-committee"
      ],
      "related_entities": [],
      "_processing": {
        "log_file_created": "2025-10-25T03:02:27Z"
      }
    },
    {
      "description": "Representative Tusler added as a cosponsor",
      "date": "2025-03-25T05:00:00+00:00",
      "organization_id": "~{\"classification\": \"upper\"}",
      "classification": [],
      "related_entities": [],
      "_processing": {
        "log_file_created": "2025-10-25T03:02:27Z"
      }
    },
    {
      "description": "Public hearing held",
      "date": "2025-05-06T05:00:00+00:00",
      "organization_id": "~{\"classification\": \"upper\"}",
      "classification": [],
      "related_entities": [],
      "_processing": {
        "log_file_created": "2025-10-25T03:02:27Z"
      }
    },
    {
      "description": "Executive action taken",
      "date": "2025-08-19T05:00:00+00:00",
      "organization_id": "~{\"classification\": \"upper\"}",
      "classification": [],
      "related_entities": [],
      "_processing": {
        "log_file_created": "2025-10-25T03:02:27Z"
      }
    },
    {
      "description": "Report passage recommended by Committee on Government Operations, Labor and Economic Development, Ayes 3, Noes 2",
      "date": "2025-08-19T05:00:00+00:00",
      "organization_id": "~{\"classification\": \"upper\"}",
      "classification": [
        "committee-passage-favorable"
      ],
      "related_entities": [],
      "_processing": {
        "log_file_created": "2025-10-25T03:02:27Z"
      }
    },
    {
      "description": "Available for scheduling",
      "date": "2025-08-19T05:00:00+00:00",
      "organization_id": "~{\"classification\": \"upper\"}",
      "classification": [],
      "related_entities": [],
      "_processing": {
        "log_file_created": "2025-10-25T03:02:27Z"
      }
    }
  ],
  "sponsorships": [
    {
      "name": "Hutton",
      "classification": "primary",
      "entity_type": "person",
      "primary": true,
      "person_id": "~{\"chamber\": \"upper\", \"name\": \"Hutton\"}",
      "organization_id": null
    },
    {
      "name": "Nass",
      "classification": "primary",
      "entity_type": "person",
      "primary": true,
      "person_id": "~{\"chamber\": \"upper\", \"name\": \"Nass\"}",
      "organization_id": null
    },
    {
      "name": "Tomczyk",
      "classification": "primary",
      "entity_type": "person",
      "primary": true,
      "person_id": "~{\"chamber\": \"upper\", \"name\": \"Tomczyk\"}",
      "organization_id": null
    },
    {
      "name": "Kapenga",
      "classification": "primary",
      "entity_type": "person",
      "primary": true,
      "person_id": "~{\"chamber\": \"upper\", \"name\": \"Kapenga\"}",
      "organization_id": null
    }
  ],
  "related_bills": [],
  "versions": [
    {
      "note": "Bill Text",
      "links": [
        {
          "url": "https://docs.legis.wisconsin.gov/document/proposaltext/2025/REG/SB151",
          "media_type": "text/html"
        },
        {
          "url": "https://docs.legis.wisconsin.gov/document/proposaltext/2025/REG/SB151.pdf",
          "media_type": "application/pdf"
        }
      ],
      "date": "",
      "classification": ""
    }
  ],
  "documents": [
    {
      "note": "SB151 ROCP for Committee on Government Operations, Labor and Economic Development On 8/19/2025",
      "links": [
        {
          "url": "https://docs.legis.wisconsin.gov/2025/related/records/senate/government_operations_labor_and_economic_development/1938083",
          "media_type": "text/html"
        }
      ],
      "date": "",
      "classification": ""
    },
    {
      "note": "LC Bill Hearing Materials",
      "links": [
        {
          "url": "https://docs.legis.wisconsin.gov/document/lcbillhearingtestimonyandmaterials/2025/REG/SB151",
          "media_type": "text/html"
        }
      ],
      "date": "",
      "classification": ""
    },
    {
      "note": "Wisconsin Ethics Commission information",
      "links": [
        {
          "url": "https://lobbying.wi.gov/What/BillInformation/2025REG/BillKey/REGSB151",
          "media_type": "text/html"
        }
      ],
      "date": "",
      "classification": ""
    },
    {
      "note": "2025 Assembly Bill 146",
      "links": [
        {
          "url": "https://docs.legis.wisconsin.gov/2025/proposals/ab146",
          "media_type": "text/html"
        }
      ],
      "date": "",
      "classification": ""
    }
  ],
  "citations": [],
  "sources": [
    {
      "url": "https://docs.legis.wisconsin.gov/2025/proposals/reg/sen/bill/sb151",
      "note": ""
    }
  ],
  "extras": {
    "status": "Status: S - Hold (Available for Scheduling)"
  },
  "jurisdiction": {
    "id": "ocd-jurisdiction/country:us/state:wi/government",
    "name": "Wisconsin",
    "classification": "state",
    "division_id": "ocd-division/country:us/state:wi"
  },
  "_processing": {
    "logs_latest_update": "2025-10-25T03:02:27Z"
  }
}